MANIFEST.in
README.rst
requirements.txt
setup.py
presence/__init__.py
presence/__main__.py
presence.egg-info/PKG-INFO
presence.egg-info/SOURCES.txt
presence.egg-info/dependency_links.txt
presence.egg-info/entry_points.txt
presence.egg-info/requires.txt
presence.egg-info/top_level.txt