Metadata-Version: 1.1
Name: presence
Version: 0.2
Summary: Presence
Home-page: http://srcco.de/
Author: Henning Jacobs
Author-email: henning@jacobs1.de
License: Apache License 2.0
Keywords: presence attendance uptime
Platform: UNKNOWN
Classifier: Development Status :: 4 - Beta
Classifier: Programming Language :: Python
Classifier: Programming Language :: Python :: 3.4
Classifier: Programming Language :: Python :: Implementation :: CPython
Classifier: Operating System :: POSIX :: Linux
Classifier: License :: OSI Approved :: Apache Software License
